ronds_sdk/__init__.py
ronds_sdk/error.py
ronds_sdk/logger_config.py
ronds_sdk/logging_config.yml
ronds_sdk/pipeline.py
ronds_sdk/dataframe/__init__.py
ronds_sdk/dataframe/pvalue.py
ronds_sdk/dataframe/window.py
ronds_sdk/datasources/__init__.py
ronds_sdk/datasources/cassandra_manager.py
ronds_sdk/datasources/es_manager.py
ronds_sdk/datasources/http_manager.py
ronds_sdk/datasources/kafka_manager.py
ronds_sdk/datasources/minio_manager.py
ronds_sdk/datasources/redis_manager.py
ronds_sdk/ml/__init__.py
ronds_sdk/models/__init__.py
ronds_sdk/models/data.py
ronds_sdk/options/__init__.py
ronds_sdk/options/pipeline_options.py
ronds_sdk/options/value_provider.py
ronds_sdk/parser/__init__.py
ronds_sdk/parser/arg_parser.py
ronds_sdk/parser/dag_parser.py
ronds_sdk/parser/rule_parser.py
ronds_sdk/runners/__init__.py
ronds_sdk/runners/pipeline_context.py
ronds_sdk/runners/python_runner.py
ronds_sdk/runners/ray_runner.py
ronds_sdk/runners/runner.py
ronds_sdk/runners/spark_runner.py
ronds_sdk/runners/planners/__init__.py
ronds_sdk/runners/planners/core_rules.py
ronds_sdk/runners/planners/parallel_rule.py
ronds_sdk/runners/planners/ray_basic_rule.py
ronds_sdk/runners/planners/ray_remote_rule.py
ronds_sdk/runners/visitors/__init__.py
ronds_sdk/runners/visitors/spark_runner_visitor.py
ronds_sdk/templates/__init__.py
ronds_sdk/templates/phm_rule_base_ray.py
ronds_sdk/templates/phm_rules_editor.py
ronds_sdk/templates/phm_rules_editor_ray.py
ronds_sdk/tools/__init__.py
ronds_sdk/tools/buffer.py
ronds_sdk/tools/buffer_utils.py
ronds_sdk/tools/cache.py
ronds_sdk/tools/constants.py
ronds_sdk/tools/data_utils.py
ronds_sdk/tools/exception_utils.py
ronds_sdk/tools/file_utils.py
ronds_sdk/tools/graph_utils.py
ronds_sdk/tools/json_utils.py
ronds_sdk/tools/metaclass.py
ronds_sdk/tools/networkx_util.py
ronds_sdk/tools/schedule.py
ronds_sdk/tools/shuffle.py
ronds_sdk/tools/stateful_job.py
ronds_sdk/tools/utils.py
ronds_sdk/tools/window.py
ronds_sdk/transforms/__init__.py
rondsspark-0.0.4.51.dist-info/METADATA
rondsspark-0.0.4.51.dist-info/WHEEL
rondsspark-0.0.4.51.dist-info/top_level.txt
rondsspark-0.0.4.51.dist-info/RECORD
